adafruit_board_toolkit/__init__.py
adafruit_board_toolkit/_list_ports_osx.py
adafruit_board_toolkit/_list_ports_windows.py
adafruit_board_toolkit/circuitpython_serial.py
adafruit_board_toolkit-1.1.1.dist-info/LICENSE
adafruit_board_toolkit-1.1.1.dist-info/METADATA
adafruit_board_toolkit-1.1.1.dist-info/WHEEL
adafruit_board_toolkit-1.1.1.dist-info/top_level.txt
adafruit_board_toolkit-1.1.1.dist-info/RECORD
