Metadata-Version: 2.1
Name: adafruit-board-toolkit
Version: 1.1.1
Summary: CircuitPython board identification and information
Home-page: https://github.com/adafruit/Adafruit_Board_Toolkit
Author: Adafruit Industries
Author-email: circuitpython@adafruit.com
License: MIT
Keywords: adafruit circuitpython micropython board_toolkit
Classifier: Development Status :: 3 - Alpha
Classifier: Intended Audience :: Developers
Classifier: Topic :: Software Development :: Libraries
Classifier: Topic :: System :: Hardware
Classifier: License :: OSI Approved :: MIT License
Classifier: Programming Language :: Python :: 3
Classifier: Programming Language :: Python :: 3.5
Requires-Python: >=3.5.0
License-File: LICENSE
